{
  "id": "9f258efe-dbfc-4675-95b1-4d0f9085e548",
  "prevId": "a43bbff1-3204-4057-9cc6-fde162015725",
  "version": "7",
  "dialect": "postgresql",
  "tables": {
    "public.channels": {
      "name": "channels",
      "schema": "",
      "columns": {
        "id": {
          "name": "id",
          "type": "uuid",
          "primaryKey": true,
          "notNull": true,
          "default": "gen_random_uuid()"
        },
        "community_id": {
          "name": "community_id",
          "type": "uuid",
          "primaryKey": false,
          "notNull": true
        },
        "name": {
          "name": "name",
          "type": "text",
          "primaryKey": false,
          "notNull": true
        },
        "created_at": {
          "name": "created_at",
          "type": "timestamp",
          "primaryKey": false,
          "notNull": true,
          "default": "now()"
        }
      },
      "indexes": {
        "channels_community_idx": {
          "name": "channels_community_idx",
          "columns": [
            {
              "expression": "community_id",
              "isExpression": false,
              "asc": true,
              "nulls": "last"
            }
          ],
          "isUnique": false,
          "concurrently": false,
          "method": "btree",
          "with": {}
        }
      },
      "foreignKeys": {
        "channels_community_id_communities_id_fk": {
          "name": "channels_community_id_communities_id_fk",
          "tableFrom": "channels",
          "tableTo": "communities",
          "columnsFrom": [
            "community_id"
          ],
          "columnsTo": [
            "id"
          ],
          "onDelete": "no action",
          "onUpdate": "no action"
        }
      },
      "compositePrimaryKeys": {},
      "uniqueConstraints": {}
    },
    "public.communities": {
      "name": "communities",
      "schema": "",
      "columns": {
        "id": {
          "name": "id",
          "type": "uuid",
          "primaryKey": true,
          "notNull": true,
          "default": "gen_random_uuid()"
        },
        "name": {
          "name": "name",
          "type": "text",
          "primaryKey": false,
          "notNull": true
        },
        "icon_url": {
          "name": "icon_url",
          "type": "text",
          "primaryKey": false,
          "notNull": false
        },
        "invite_code": {
          "name": "invite_code",
          "type": "text",
          "primaryKey": false,
          "notNull": true
        },
        "created_by": {
          "name": "created_by",
          "type": "uuid",
          "primaryKey": false,
          "notNull": true
        },
        "created_at": {
          "name": "created_at",
          "type": "timestamp",
          "primaryKey": false,
          "notNull": true,
          "default": "now()"
        }
      },
      "indexes": {},
      "foreignKeys": {
        "communities_created_by_users_id_fk": {
          "name": "communities_created_by_users_id_fk",
          "tableFrom": "communities",
          "tableTo": "users",
          "columnsFrom": [
            "created_by"
          ],
          "columnsTo": [
            "id"
          ],
          "onDelete": "no action",
          "onUpdate": "no action"
        }
      },
      "compositePrimaryKeys": {},
      "uniqueConstraints": {
        "communities_invite_code_unique": {
          "name": "communities_invite_code_unique",
          "nullsNotDistinct": false,
          "columns": [
            "invite_code"
          ]
        }
      }
    },
    "public.community_members": {
      "name": "community_members",
      "schema": "",
      "columns": {
        "id": {
          "name": "id",
          "type": "uuid",
          "primaryKey": true,
          "notNull": true,
          "default": "gen_random_uuid()"
        },
        "community_id": {
          "name": "community_id",
          "type": "uuid",
          "primaryKey": false,
          "notNull": true
        },
        "user_id": {
          "name": "user_id",
          "type": "uuid",
          "primaryKey": false,
          "notNull": true
        },
        "joined_at": {
          "name": "joined_at",
          "type": "timestamp",
          "primaryKey": false,
          "notNull": true,
          "default": "now()"
        }
      },
      "indexes": {
        "community_members_community_idx": {
          "name": "community_members_community_idx",
          "columns": [
            {
              "expression": "community_id",
              "isExpression": false,
              "asc": true,
              "nulls": "last"
            }
          ],
          "isUnique": false,
          "concurrently": false,
          "method": "btree",
          "with": {}
        },
        "community_members_user_idx": {
          "name": "community_members_user_idx",
          "columns": [
            {
              "expression": "user_id",
              "isExpression": false,
              "asc": true,
              "nulls": "last"
            }
          ],
          "isUnique": false,
          "concurrently": false,
          "method": "btree",
          "with": {}
        }
      },
      "foreignKeys": {
        "community_members_community_id_communities_id_fk": {
          "name": "community_members_community_id_communities_id_fk",
          "tableFrom": "community_members",
          "tableTo": "communities",
          "columnsFrom": [
            "community_id"
          ],
          "columnsTo": [
            "id"
          ],
          "onDelete": "no action",
          "onUpdate": "no action"
        },
        "community_members_user_id_users_id_fk": {
          "name": "community_members_user_id_users_id_fk",
          "tableFrom": "community_members",
          "tableTo": "users",
          "columnsFrom": [
            "user_id"
          ],
          "columnsTo": [
            "id"
          ],
          "onDelete": "no action",
          "onUpdate": "no action"
        }
      },
      "compositePrimaryKeys": {},
      "uniqueConstraints": {}
    },
    "public.emojis": {
      "name": "emojis",
      "schema": "",
      "columns": {
        "id": {
          "name": "id",
          "type": "uuid",
          "primaryKey": true,
          "notNull": true,
          "default": "gen_random_uuid()"
        },
        "community_id": {
          "name": "community_id",
          "type": "uuid",
          "primaryKey": false,
          "notNull": true
        },
        "name": {
          "name": "name",
          "type": "text",
          "primaryKey": false,
          "notNull": true
        },
        "file_url": {
          "name": "file_url",
          "type": "text",
          "primaryKey": false,
          "notNull": true
        },
        "animated": {
          "name": "animated",
          "type": "boolean",
          "primaryKey": false,
          "notNull": true,
          "default": false
        },
        "uploaded_by": {
          "name": "uploaded_by",
          "type": "uuid",
          "primaryKey": false,
          "notNull": true
        },
        "created_at": {
          "name": "created_at",
          "type": "timestamp",
          "primaryKey": false,
          "notNull": true,
          "default": "now()"
        }
      },
      "indexes": {
        "emojis_community_idx": {
          "name": "emojis_community_idx",
          "columns": [
            {
              "expression": "community_id",
              "isExpression": false,
              "asc": true,
              "nulls": "last"
            }
          ],
          "isUnique": false,
          "concurrently": false,
          "method": "btree",
          "with": {}
        }
      },
      "foreignKeys": {
        "emojis_community_id_communities_id_fk": {
          "name": "emojis_community_id_communities_id_fk",
          "tableFrom": "emojis",
          "tableTo": "communities",
          "columnsFrom": [
            "community_id"
          ],
          "columnsTo": [
            "id"
          ],
          "onDelete": "no action",
          "onUpdate": "no action"
        },
        "emojis_uploaded_by_users_id_fk": {
          "name": "emojis_uploaded_by_users_id_fk",
          "tableFrom": "emojis",
          "tableTo": "users",
          "columnsFrom": [
            "uploaded_by"
          ],
          "columnsTo": [
            "id"
          ],
          "onDelete": "no action",
          "onUpdate": "no action"
        }
      },
      "compositePrimaryKeys": {},
      "uniqueConstraints": {}
    },
    "public.messages": {
      "name": "messages",
      "schema": "",
      "columns": {
        "id": {
          "name": "id",
          "type": "uuid",
          "primaryKey": true,
          "notNull": true,
          "default": "gen_random_uuid()"
        },
        "channel_id": {
          "name": "channel_id",
          "type": "uuid",
          "primaryKey": false,
          "notNull": true
        },
        "sender_id": {
          "name": "sender_id",
          "type": "uuid",
          "primaryKey": false,
          "notNull": true
        },
        "ciphertext": {
          "name": "ciphertext",
          "type": "text",
          "primaryKey": false,
          "notNull": true
        },
        "reply_to_id": {
          "name": "reply_to_id",
          "type": "uuid",
          "primaryKey": false,
          "notNull": false
        },
        "created_at": {
          "name": "created_at",
          "type": "timestamp",
          "primaryKey": false,
          "notNull": true,
          "default": "now()"
        }
      },
      "indexes": {
        "messages_channel_idx": {
          "name": "messages_channel_idx",
          "columns": [
            {
              "expression": "channel_id",
              "isExpression": false,
              "asc": true,
              "nulls": "last"
            }
          ],
          "isUnique": false,
          "concurrently": false,
          "method": "btree",
          "with": {}
        },
        "messages_created_at_idx": {
          "name": "messages_created_at_idx",
          "columns": [
            {
              "expression": "created_at",
              "isExpression": false,
              "asc": true,
              "nulls": "last"
            }
          ],
          "isUnique": false,
          "concurrently": false,
          "method": "btree",
          "with": {}
        }
      },
      "foreignKeys": {
        "messages_channel_id_channels_id_fk": {
          "name": "messages_channel_id_channels_id_fk",
          "tableFrom": "messages",
          "tableTo": "channels",
          "columnsFrom": [
            "channel_id"
          ],
          "columnsTo": [
            "id"
          ],
          "onDelete": "no action",
          "onUpdate": "no action"
        },
        "messages_sender_id_users_id_fk": {
          "name": "messages_sender_id_users_id_fk",
          "tableFrom": "messages",
          "tableTo": "users",
          "columnsFrom": [
            "sender_id"
          ],
          "columnsTo": [
            "id"
          ],
          "onDelete": "no action",
          "onUpdate": "no action"
        }
      },
      "compositePrimaryKeys": {},
      "uniqueConstraints": {}
    },
    "public.prekeys": {
      "name": "prekeys",
      "schema": "",
      "columns": {
        "id": {
          "name": "id",
          "type": "uuid",
          "primaryKey": true,
          "notNull": true,
          "default": "gen_random_uuid()"
        },
        "user_id": {
          "name": "user_id",
          "type": "uuid",
          "primaryKey": false,
          "notNull": true
        },
        "key_id": {
          "name": "key_id",
          "type": "text",
          "primaryKey": false,
          "notNull": true
        },
        "public_key": {
          "name": "public_key",
          "type": "text",
          "primaryKey": false,
          "notNull": true
        },
        "created_at": {
          "name": "created_at",
          "type": "timestamp",
          "primaryKey": false,
          "notNull": true,
          "default": "now()"
        }
      },
      "indexes": {
        "prekeys_user_idx": {
          "name": "prekeys_user_idx",
          "columns": [
            {
              "expression": "user_id",
              "isExpression": false,
              "asc": true,
              "nulls": "last"
            }
          ],
          "isUnique": false,
          "concurrently": false,
          "method": "btree",
          "with": {}
        }
      },
      "foreignKeys": {
        "prekeys_user_id_users_id_fk": {
          "name": "prekeys_user_id_users_id_fk",
          "tableFrom": "prekeys",
          "tableTo": "users",
          "columnsFrom": [
            "user_id"
          ],
          "columnsTo": [
            "id"
          ],
          "onDelete": "no action",
          "onUpdate": "no action"
        }
      },
      "compositePrimaryKeys": {},
      "uniqueConstraints": {}
    },
    "public.reactions": {
      "name": "reactions",
      "schema": "",
      "columns": {
        "id": {
          "name": "id",
          "type": "uuid",
          "primaryKey": true,
          "notNull": true,
          "default": "gen_random_uuid()"
        },
        "message_id": {
          "name": "message_id",
          "type": "uuid",
          "primaryKey": false,
          "notNull": true
        },
        "user_id": {
          "name": "user_id",
          "type": "uuid",
          "primaryKey": false,
          "notNull": true
        },
        "emoji": {
          "name": "emoji",
          "type": "text",
          "primaryKey": false,
          "notNull": true
        },
        "created_at": {
          "name": "created_at",
          "type": "timestamp",
          "primaryKey": false,
          "notNull": true,
          "default": "now()"
        }
      },
      "indexes": {
        "reactions_message_idx": {
          "name": "reactions_message_idx",
          "columns": [
            {
              "expression": "message_id",
              "isExpression": false,
              "asc": true,
              "nulls": "last"
            }
          ],
          "isUnique": false,
          "concurrently": false,
          "method": "btree",
          "with": {}
        },
        "reactions_user_message_emoji_idx": {
          "name": "reactions_user_message_emoji_idx",
          "columns": [
            {
              "expression": "user_id",
              "isExpression": false,
              "asc": true,
              "nulls": "last"
            },
            {
              "expression": "message_id",
              "isExpression": false,
              "asc": true,
              "nulls": "last"
            },
            {
              "expression": "emoji",
              "isExpression": false,
              "asc": true,
              "nulls": "last"
            }
          ],
          "isUnique": false,
          "concurrently": false,
          "method": "btree",
          "with": {}
        }
      },
      "foreignKeys": {
        "reactions_message_id_messages_id_fk": {
          "name": "reactions_message_id_messages_id_fk",
          "tableFrom": "reactions",
          "tableTo": "messages",
          "columnsFrom": [
            "message_id"
          ],
          "columnsTo": [
            "id"
          ],
          "onDelete": "cascade",
          "onUpdate": "no action"
        },
        "reactions_user_id_users_id_fk": {
          "name": "reactions_user_id_users_id_fk",
          "tableFrom": "reactions",
          "tableTo": "users",
          "columnsFrom": [
            "user_id"
          ],
          "columnsTo": [
            "id"
          ],
          "onDelete": "no action",
          "onUpdate": "no action"
        }
      },
      "compositePrimaryKeys": {},
      "uniqueConstraints": {}
    },
    "public.sender_keys": {
      "name": "sender_keys",
      "schema": "",
      "columns": {
        "id": {
          "name": "id",
          "type": "uuid",
          "primaryKey": true,
          "notNull": true,
          "default": "gen_random_uuid()"
        },
        "channel_id": {
          "name": "channel_id",
          "type": "uuid",
          "primaryKey": false,
          "notNull": true
        },
        "user_id": {
          "name": "user_id",
          "type": "uuid",
          "primaryKey": false,
          "notNull": true
        },
        "distribution_id": {
          "name": "distribution_id",
          "type": "text",
          "primaryKey": false,
          "notNull": true
        },
        "encrypted_key": {
          "name": "encrypted_key",
          "type": "text",
          "primaryKey": false,
          "notNull": true
        },
        "for_user_id": {
          "name": "for_user_id",
          "type": "uuid",
          "primaryKey": false,
          "notNull": true
        },
        "created_at": {
          "name": "created_at",
          "type": "timestamp",
          "primaryKey": false,
          "notNull": true,
          "default": "now()"
        }
      },
      "indexes": {
        "sender_keys_channel_user_idx": {
          "name": "sender_keys_channel_user_idx",
          "columns": [
            {
              "expression": "channel_id",
              "isExpression": false,
              "asc": true,
              "nulls": "last"
            },
            {
              "expression": "for_user_id",
              "isExpression": false,
              "asc": true,
              "nulls": "last"
            }
          ],
          "isUnique": false,
          "concurrently": false,
          "method": "btree",
          "with": {}
        }
      },
      "foreignKeys": {
        "sender_keys_channel_id_channels_id_fk": {
          "name": "sender_keys_channel_id_channels_id_fk",
          "tableFrom": "sender_keys",
          "tableTo": "channels",
          "columnsFrom": [
            "channel_id"
          ],
          "columnsTo": [
            "id"
          ],
          "onDelete": "no action",
          "onUpdate": "no action"
        },
        "sender_keys_user_id_users_id_fk": {
          "name": "sender_keys_user_id_users_id_fk",
          "tableFrom": "sender_keys",
          "tableTo": "users",
          "columnsFrom": [
            "user_id"
          ],
          "columnsTo": [
            "id"
          ],
          "onDelete": "no action",
          "onUpdate": "no action"
        },
        "sender_keys_for_user_id_users_id_fk": {
          "name": "sender_keys_for_user_id_users_id_fk",
          "tableFrom": "sender_keys",
          "tableTo": "users",
          "columnsFrom": [
            "for_user_id"
          ],
          "columnsTo": [
            "id"
          ],
          "onDelete": "no action",
          "onUpdate": "no action"
        }
      },
      "compositePrimaryKeys": {},
      "uniqueConstraints": {}
    },
    "public.users": {
      "name": "users",
      "schema": "",
      "columns": {
        "id": {
          "name": "id",
          "type": "uuid",
          "primaryKey": true,
          "notNull": true,
          "default": "gen_random_uuid()"
        },
        "email": {
          "name": "email",
          "type": "text",
          "primaryKey": false,
          "notNull": true
        },
        "display_name": {
          "name": "display_name",
          "type": "text",
          "primaryKey": false,
          "notNull": true
        },
        "password_hash": {
          "name": "password_hash",
          "type": "text",
          "primaryKey": false,
          "notNull": true
        },
        "avatar_url": {
          "name": "avatar_url",
          "type": "text",
          "primaryKey": false,
          "notNull": false
        },
        "identity_key_public": {
          "name": "identity_key_public",
          "type": "text",
          "primaryKey": false,
          "notNull": false
        },
        "signed_prekey_public": {
          "name": "signed_prekey_public",
          "type": "text",
          "primaryKey": false,
          "notNull": false
        },
        "signed_prekey_signature": {
          "name": "signed_prekey_signature",
          "type": "text",
          "primaryKey": false,
          "notNull": false
        },
        "created_at": {
          "name": "created_at",
          "type": "timestamp",
          "primaryKey": false,
          "notNull": true,
          "default": "now()"
        }
      },
      "indexes": {},
      "foreignKeys": {},
      "compositePrimaryKeys": {},
      "uniqueConstraints": {
        "users_email_unique": {
          "name": "users_email_unique",
          "nullsNotDistinct": false,
          "columns": [
            "email"
          ]
        }
      }
    }
  },
  "enums": {},
  "schemas": {},
  "sequences": {},
  "_meta": {
    "columns": {},
    "schemas": {},
    "tables": {}
  }
}